parking_env/__init__.py
parking_env/parking.py
parking_env-0.0.8.dist-info/licenses/LICENSE
parking_env-0.0.8.dist-info/METADATA
parking_env-0.0.8.dist-info/WHEEL
parking_env-0.0.8.dist-info/top_level.txt
parking_env-0.0.8.dist-info/RECORD
