Metadata-Version: 2.4
Name: parking-env
Version: 0.0.8
Summary: An environment for simulated parking lot tasks.
Author-email: Kexian Shen <shenkexian@gmail.com>
License: MIT
License-File: LICENSE
Requires-Dist: gymnasium
Requires-Dist: numpy
Requires-Dist: numba
Requires-Dist: pygame
Requires-Dist: scipy
Dynamic: license-file
